<?xml version="1.0" encoding="UTF-8"?><record_update table="sc_cat_item_producer">
    <sc_cat_item_producer action="DELETE">
        <access_type>restricted</access_type>
        <active>true</active>
        <allow_edit>false</allow_edit>
        <availability>on_desktop</availability>
        <billable>false</billable>
        <can_cancel>false</can_cancel>
        <category/>
        <checked_out/>
        <cost>0</cost>
        <custom_cart/>
        <delivery_plan display_value="DEFAULT">523da512c611228900811a37c97c2014</delivery_plan>
        <delivery_plan_script/>
        <delivery_time>1970-01-03 00:00:00</delivery_time>
        <description/>
        <display_price_property>non_zero</display_price_property>
        <entitlement_script/>
        <flow_designer_flow/>
        <fulfillment_automation_level>unspecified</fulfillment_automation_level>
        <group/>
        <hide_sp>false</hide_sp>
        <icon/>
        <ignore_price>true</ignore_price>
        <image/>
        <location/>
        <mandatory_attachment>false</mandatory_attachment>
        <meta/>
        <mobile_hide_price>false</mobile_hide_price>
        <mobile_picture/>
        <mobile_picture_type>use_desktop_picture</mobile_picture_type>
        <model/>
        <name>Loaner Request</name>
        <no_attachment_v2>false</no_attachment_v2>
        <no_cart>false</no_cart>
        <no_cart_v2>false</no_cart_v2>
        <no_delivery_time_v2>false</no_delivery_time_v2>
        <no_order>false</no_order>
        <no_order_now>false</no_order_now>
        <no_proceed_checkout>false</no_proceed_checkout>
        <no_quantity>false</no_quantity>
        <no_quantity_v2>false</no_quantity_v2>
        <no_search>false</no_search>
        <no_wishlist_v2>false</no_wishlist_v2>
        <omit_price>false</omit_price>
        <order>0</order>
        <ordered_item_link/>
        <owner display_value="System Administrator">6816f79cc0a8016401c5a33be04be441</owner>
        <picture/>
        <post_insert_script><![CDATA[/**
* This script is executed after the record is generated. 
* `current` Is the GlideRecord produced by Record Producer. Use `current.update()` to update the record
* To access the variables, use `producer.var1` where var1 is the name of the variable
* To access the Record Producer use `cat_item`
*/]]></post_insert_script>
        <preview>JavaScript: popupOpenStandard("com.glideapp.servicecatalog_cat_item_view.do?v=1&amp;sysparm_id=c52e18af831212107f44d9aeddda1ebc&amp;sysparm_preview=true", "summary");</preview>
        <published_ref/>
        <recurring_frequency/>
        <redirect_url>generated_record</redirect_url>
        <request_method/>
        <roles/>
        <save_options/>
        <save_script><![CDATA[/**
* This script is executed at every step save in Catalog Builder. 
* This script is executed before `Script` is executed.
* `current` Is the GlideRecord produced by Record Producer. 
* To access the variables, use `producer.var1` where var1 is the name of the variable
* To access the Record Producer use `cat_item`
*/]]></save_script>
        <sc_catalogs/>
        <sc_ic_item_staging/>
        <sc_ic_version/>
        <sc_template/>
        <script><![CDATA[/** This script is executed before the Record is generated
* `current`- GlideRecord produced by Record Producer
* Don't use `current.update()` or `current.insert()` as the record is generated by Record Producer
* Don't use `current.setValue('sys_class_name', 'xxx')` as this will trigger reparent flow and can cause data loss
* Avoid `current.setAbortAction()` and generate a separate record
* Use `producer.var1` to access variables
*/]]></script>
        <short_description>Submit a New Loaner Request</short_description>
        <show_variable_help_on_load>false</show_variable_help_on_load>
        <start_closed>false</start_closed>
        <state/>
        <sys_class_name>sc_cat_item_producer</sys_class_name>
        <sys_created_by>admin</sys_created_by>
        <sys_created_on>2024-12-11 20:10:32</sys_created_on>
        <sys_id>c52e18af831212107f44d9aeddda1ebc</sys_id>
        <sys_mod_count>21</sys_mod_count>
        <sys_name>Loaner Request</sys_name>
        <sys_package display_value="Loaner Request" source="x_cdltd_loaner_req">199adb92830212107f44d9aeddda1e53</sys_package>
        <sys_policy/>
        <sys_scope display_value="Loaner Request">199adb92830212107f44d9aeddda1e53</sys_scope>
        <sys_update_name>sc_cat_item_producer_c52e18af831212107f44d9aeddda1ebc</sys_update_name>
        <sys_updated_by>admin</sys_updated_by>
        <sys_updated_on>2024-12-11 20:17:46</sys_updated_on>
        <table_name>x_cdltd_loaner_req_loaner_request</table_name>
        <taxonomy_topic/>
        <template/>
        <template_manager_roles/>
        <type>item</type>
        <use_sc_layout>true</use_sc_layout>
        <vendor/>
        <version>22</version>
        <view/>
        <visible_bundle>true</visible_bundle>
        <visible_guide>true</visible_guide>
        <visible_standalone>true</visible_standalone>
        <workflow/>
    </sc_cat_item_producer>
    <sys_translated_text action="DELETE" query="documentkey=c52e18af831212107f44d9aeddda1ebc"/>
    <fx_price action="DELETE" query="id=c52e18af831212107f44d9aeddda1ebc"/>
    <sys_update_version action="INSERT_OR_UPDATE">
        <action>DELETE</action>
        <application display_value="Loaner Request">199adb92830212107f44d9aeddda1e53</application>
        <file_path/>
        <instance_id>b142f416c3c296d0d7299dcd2b013114</instance_id>
        <instance_name>nowlearning-nlinst02256130-0001</instance_name>
        <name>sc_cat_item_producer_c52e18af831212107f44d9aeddda1ebc</name>
        <payload>&lt;?xml version="1.0" encoding="UTF-8"?&gt;&lt;record_update table="sc_cat_item_producer"&gt;&lt;sc_cat_item_producer action="INSERT_OR_UPDATE"&gt;&lt;access_type&gt;restricted&lt;/access_type&gt;&lt;active&gt;true&lt;/active&gt;&lt;allow_edit&gt;false&lt;/allow_edit&gt;&lt;availability&gt;on_desktop&lt;/availability&gt;&lt;billable&gt;false&lt;/billable&gt;&lt;can_cancel&gt;false&lt;/can_cancel&gt;&lt;category/&gt;&lt;checked_out/&gt;&lt;cost&gt;0&lt;/cost&gt;&lt;custom_cart/&gt;&lt;delivery_plan display_value="DEFAULT"&gt;523da512c611228900811a37c97c2014&lt;/delivery_plan&gt;&lt;delivery_plan_script/&gt;&lt;delivery_time&gt;1970-01-03 00:00:00&lt;/delivery_time&gt;&lt;description/&gt;&lt;display_price_property&gt;non_zero&lt;/display_price_property&gt;&lt;entitlement_script/&gt;&lt;flow_designer_flow/&gt;&lt;fulfillment_automation_level&gt;unspecified&lt;/fulfillment_automation_level&gt;&lt;group/&gt;&lt;hide_sp&gt;false&lt;/hide_sp&gt;&lt;icon/&gt;&lt;ignore_price&gt;true&lt;/ignore_price&gt;&lt;image/&gt;&lt;location/&gt;&lt;mandatory_attachment&gt;false&lt;/mandatory_attachment&gt;&lt;meta/&gt;&lt;mobile_hide_price&gt;false&lt;/mobile_hide_price&gt;&lt;mobile_picture/&gt;&lt;mobile_picture_type&gt;use_desktop_picture&lt;/mobile_picture_type&gt;&lt;model/&gt;&lt;name&gt;Loaner Request&lt;/name&gt;&lt;no_attachment_v2&gt;false&lt;/no_attachment_v2&gt;&lt;no_cart&gt;false&lt;/no_cart&gt;&lt;no_cart_v2&gt;false&lt;/no_cart_v2&gt;&lt;no_delivery_time_v2&gt;false&lt;/no_delivery_time_v2&gt;&lt;no_order&gt;false&lt;/no_order&gt;&lt;no_order_now&gt;false&lt;/no_order_now&gt;&lt;no_proceed_checkout&gt;false&lt;/no_proceed_checkout&gt;&lt;no_quantity&gt;false&lt;/no_quantity&gt;&lt;no_quantity_v2&gt;false&lt;/no_quantity_v2&gt;&lt;no_search&gt;false&lt;/no_search&gt;&lt;no_wishlist_v2&gt;false&lt;/no_wishlist_v2&gt;&lt;omit_price&gt;false&lt;/omit_price&gt;&lt;order&gt;0&lt;/order&gt;&lt;ordered_item_link/&gt;&lt;owner display_value="System Administrator"&gt;6816f79cc0a8016401c5a33be04be441&lt;/owner&gt;&lt;picture/&gt;&lt;post_insert_script&gt;&lt;![CDATA[/**
* This script is executed after the record is generated. 
* `current` Is the GlideRecord produced by Record Producer. Use `current.update()` to update the record
* To access the variables, use `producer.var1` where var1 is the name of the variable
* To access the Record Producer use `cat_item`
*/]]&gt;&lt;/post_insert_script&gt;&lt;preview&gt;JavaScript: popupOpenStandard("com.glideapp.servicecatalog_cat_item_view.do?v=1&amp;amp;sysparm_id=c52e18af831212107f44d9aeddda1ebc&amp;amp;sysparm_preview=true", "summary");&lt;/preview&gt;&lt;published_ref/&gt;&lt;recurring_frequency/&gt;&lt;redirect_url&gt;generated_record&lt;/redirect_url&gt;&lt;request_method/&gt;&lt;roles/&gt;&lt;save_options/&gt;&lt;save_script&gt;&lt;![CDATA[/**
* This script is executed at every step save in Catalog Builder. 
* This script is executed before `Script` is executed.
* `current` Is the GlideRecord produced by Record Producer. 
* To access the variables, use `producer.var1` where var1 is the name of the variable
* To access the Record Producer use `cat_item`
*/]]&gt;&lt;/save_script&gt;&lt;sc_catalogs/&gt;&lt;sc_ic_item_staging/&gt;&lt;sc_ic_version/&gt;&lt;sc_template/&gt;&lt;script&gt;&lt;![CDATA[/** This script is executed before the Record is generated
* `current`- GlideRecord produced by Record Producer
* Don't use `current.update()` or `current.insert()` as the record is generated by Record Producer
* Don't use `current.setValue('sys_class_name', 'xxx')` as this will trigger reparent flow and can cause data loss
* Avoid `current.setAbortAction()` and generate a separate record
* Use `producer.var1` to access variables
*/]]&gt;&lt;/script&gt;&lt;short_description&gt;Submit a New Loaner Request&lt;/short_description&gt;&lt;show_variable_help_on_load&gt;false&lt;/show_variable_help_on_load&gt;&lt;start_closed&gt;false&lt;/start_closed&gt;&lt;state/&gt;&lt;sys_class_name&gt;sc_cat_item_producer&lt;/sys_class_name&gt;&lt;sys_created_by&gt;admin&lt;/sys_created_by&gt;&lt;sys_created_on&gt;2024-12-11 20:10:32&lt;/sys_created_on&gt;&lt;sys_id&gt;c52e18af831212107f44d9aeddda1ebc&lt;/sys_id&gt;&lt;sys_mod_count&gt;21&lt;/sys_mod_count&gt;&lt;sys_name&gt;Loaner Request&lt;/sys_name&gt;&lt;sys_package display_value="Loaner Request" source="x_cdltd_loaner_req"&gt;199adb92830212107f44d9aeddda1e53&lt;/sys_package&gt;&lt;sys_policy/&gt;&lt;sys_scope display_value="Loaner Request"&gt;199adb92830212107f44d9aeddda1e53&lt;/sys_scope&gt;&lt;sys_update_name&gt;sc_cat_item_producer_c52e18af831212107f44d9aeddda1ebc&lt;/sys_update_name&gt;&lt;sys_updated_by&gt;admin&lt;/sys_updated_by&gt;&lt;sys_updated_on&gt;2024-12-11 20:17:46&lt;/sys_updated_on&gt;&lt;table_name&gt;x_cdltd_loaner_req_loaner_request&lt;/table_name&gt;&lt;taxonomy_topic/&gt;&lt;template/&gt;&lt;template_manager_roles/&gt;&lt;type&gt;item&lt;/type&gt;&lt;use_sc_layout&gt;true&lt;/use_sc_layout&gt;&lt;vendor/&gt;&lt;version&gt;22&lt;/version&gt;&lt;view/&gt;&lt;visible_bundle&gt;true&lt;/visible_bundle&gt;&lt;visible_guide&gt;true&lt;/visible_guide&gt;&lt;visible_standalone&gt;true&lt;/visible_standalone&gt;&lt;workflow/&gt;&lt;/sc_cat_item_producer&gt;&lt;sys_translated_text action="delete_multiple" query="documentkey=c52e18af831212107f44d9aeddda1ebc"/&gt;&lt;fx_price action="delete_multiple" query="id=c52e18af831212107f44d9aeddda1ebc"/&gt;&lt;/record_update&gt;</payload>
        <payload_hash>-913848554</payload_hash>
        <record_name>Loaner Request</record_name>
        <reverted_from/>
        <source>e7f951f2834212107f44d9aeddda1e12</source>
        <source_table>sys_update_set</source_table>
        <state>previous</state>
        <sys_created_by>admin</sys_created_by>
        <sys_created_on>2024-12-11 20:17:46</sys_created_on>
        <sys_id>83cf54a3835212107f44d9aeddda1ec2</sys_id>
        <sys_mod_count>0</sys_mod_count>
        <sys_recorded_at>193b75ed9210000001</sys_recorded_at>
        <sys_updated_by>admin</sys_updated_by>
        <sys_updated_on>2024-12-11 20:17:46</sys_updated_on>
        <type>Record Producer</type>
        <update_guid>8bcf54a3dc52121062a892e885fb22c1</update_guid>
        <update_guid_history>8bcf54a3dc52121062a892e885fb22c1:-913848554,4a2e58efd11212109877f89b2c9b9128:84257843,0e2e58efdd121210dcc3e048c125fd19:172246557,f52e58efc2121210f9afe38c79c1bf0b:-1971237604,b92e58eff91212107fea5d06e4826c02:180245531,fd2e18ef8e121210ccbfd8c6120579fa:-1963238630,352e18ef251212107172c1e46f6d6cf3:188244505,792e18ef0c1212107c61d8fe843995eb:-1955239656,f52e18ef631212105298ca83a29a93d7:196243479,3d2e18ef0f121210ff5a8124ec466bcf:-1947240682,b92e18ef57121210c4c5b8fba36d62bb:204242453,a92e18ef9512121050fbbb8286a83e96:-1939241708,ad2e18ef371212101250269bfbb86470:1169944950,ad2e18efc01212109998731749bc5a57:-973539211,612e18ef44121210b21fd10727c11c4f:1177943924,a52e18efda12121034e1b891e0b4bd47:-965540237,252e18ef33121210ef5fcde0a5dae633:1185942898,192e18ef5612121015cd9c0004417d28:-957541263,912e18efdf121210739da04e41988604:1193941872,9d2e18ef54121210579bc3ba9e326506:-949542289,192ed4efc112121044c5271723c59ce9:205461821,d92ed4effb1212104522d8bc90cbbce2:1779711072</update_guid_history>
    </sys_update_version>
    <sys_metadata_delete action="INSERT_OR_UPDATE">
        <sys_audit_delete display_value="Loaner Request">d3cf54a3835212107f44d9aeddda1eed</sys_audit_delete>
        <sys_class_name>sys_metadata_delete</sys_class_name>
        <sys_created_by>admin</sys_created_by>
        <sys_created_on>2024-12-11 20:17:47</sys_created_on>
        <sys_db_object display_value="" name="sc_cat_item_producer">sc_cat_item_producer</sys_db_object>
        <sys_id>088d1570d57445c4812f67b457a43f10</sys_id>
        <sys_metadata>c52e18af831212107f44d9aeddda1ebc</sys_metadata>
        <sys_mod_count>0</sys_mod_count>
        <sys_name>Loaner Request</sys_name>
        <sys_package display_value="Loaner Request" source="x_cdltd_loaner_req">199adb92830212107f44d9aeddda1e53</sys_package>
        <sys_parent display_value="Loaner Request">4d916b9a830212107f44d9aeddda1e1a</sys_parent>
        <sys_policy/>
        <sys_scope display_value="Loaner Request">199adb92830212107f44d9aeddda1e53</sys_scope>
        <sys_scope_delete display_value="">52636578c11c43f083b513a86ec8a640</sys_scope_delete>
        <sys_update_name>sc_cat_item_producer_c52e18af831212107f44d9aeddda1ebc</sys_update_name>
        <sys_update_version display_value="sc_cat_item_producer_c52e18af831212107f44d9aeddda1ebc">83cf54a3835212107f44d9aeddda1ec2</sys_update_version>
        <sys_updated_by>admin</sys_updated_by>
        <sys_updated_on>2024-12-11 20:17:47</sys_updated_on>
    </sys_metadata_delete>
</record_update>
